{
  "lang":"en",
  "name":"pipeline",
  "version":"0.0.0",
  "spacy_version":">=3.8.14,<3.9.0",
  "description":"",
  "author":"",
  "email":"",
  "url":"",
  "license":"",
  "spacy_git_version":"0069cf9",
  "vectors":{
    "width":0,
    "vectors":0,
    "keys":0,
    "name":null,
    "mode":"default"
  },
  "labels":{
    "tok2vec":[

    ],
    "ner":[
      "CC_RECIPIENT",
      "CC_RECIPIENT_EMAIL",
      "DATE",
      "RECIPIENT",
      "RECIPIENT_EMAIL",
      "SENDER",
      "SENDER_EMAIL",
      "SUBJECT"
    ]
  },
  "pipeline":[
    "tok2vec",
    "ner"
  ],
  "components":[
    "tok2vec",
    "ner"
  ],
  "disabled":[

  ],
  "performance":{
    "ents_f":0.480565371,
    "ents_p":0.5074626866,
    "ents_r":0.4563758389,
    "ents_per_type":{
      "SENDER":{
        "p":0.4,
        "r":0.4,
        "f":0.4
      },
      "DATE":{
        "p":1.0,
        "r":0.9375,
        "f":0.9677419355
      },
      "SUBJECT":{
        "p":0.6,
        "r":0.5454545455,
        "f":0.5714285714
      },
      "RECIPIENT":{
        "p":0.5161290323,
        "r":0.4102564103,
        "f":0.4571428571
      },
      "SENDER_EMAIL":{
        "p":0.3076923077,
        "r":0.2857142857,
        "f":0.2962962963
      },
      "RECIPIENT_EMAIL":{
        "p":0.6666666667,
        "r":0.4651162791,
        "f":0.5479452055
      },
      "CC_RECIPIENT_EMAIL":{
        "p":0.0588235294,
        "r":0.2,
        "f":0.0909090909
      },
      "CC_RECIPIENT":{
        "p":0.0,
        "r":0.0,
        "f":0.0
      }
    },
    "tok2vec_loss":110.3477254275,
    "ner_loss":148.4117584229
  }
}